betqstat/__init__.py
betqstat/ev.py
betqstat/impliedprob.py
betqstat/ladder.py
betqstat/odds.py
betqstat/rank.py
betqstat/stake.py
betqstat-0.0.1.dist-info/LICENSE
betqstat-0.0.1.dist-info/METADATA
betqstat-0.0.1.dist-info/WHEEL
betqstat-0.0.1.dist-info/top_level.txt
betqstat-0.0.1.dist-info/RECORD
