Metadata-Version: 2.1
Name: betqstat
Version: 0.0.1
Summary: A Python package for wagering related statistical functions and analysis
Author-email: Jeremy Walsh <jeremypaul.walsh@gmail.com>
License: MIT License
Project-URL: Homepage, https://jemjemwalsh.github.io/betqstat
Project-URL: Documentation, https://jemjemwalsh.github.io/betqstat
Project-URL: Source, https://github.com/jemjemwalsh/betqstat
Keywords: bet,betting,wagering,odds,expected value,ev,bookmaker,bookie,betfair,probability,implied probability,staking
Classifier: License :: OSI Approved :: MIT License
Classifier: Programming Language :: Python
Classifier: Programming Language :: Python :: 3
Classifier: Programming Language :: Python :: 3 :: Only
Requires-Python: <4,>=3.8
License-File: LICENSE
Requires-Dist: pandas (>=1.5)
Requires-Dist: scipy (>=1.9.0)
Provides-Extra: dev
Requires-Dist: mkdocs (~=1.4.2) ; extra == 'dev'
Requires-Dist: mkdocs-material (~=8.5.11) ; extra == 'dev'
Requires-Dist: mkdocs-jupyter (~=0.22.0) ; extra == 'dev'
Requires-Dist: black (~=22.10.0) ; extra == 'dev'
Requires-Dist: pytest (~=7.2.0) ; extra == 'dev'
Requires-Dist: pytest-cov (~=4.0.0) ; extra == 'dev'
Requires-Dist: jupyter (~=1.0.0) ; extra == 'dev'
Requires-Dist: matplotlib (~=3.6.2) ; extra == 'dev'
